Workbook

Sheet Instrucciones
A1: Modelo financiero — Law Offices of Jose R. Santiago, PLLC
A2: Instrumento del Anexo A del documento de modelo de negocio. Versión 1.0
B4: Cómo usar este archivo
B5: 1. | C5: Sustituye los valores de ejemplo por los datos reales de la firma. Los valores precargados vienen del documento de modelo de negocio y son ILUSTRATIVOS: sirven para que el modelo funcione desde el primer momento, no para describir la firma.
B6: 2. | C6: Escribe únicamente en las celdas con fondo amarillo. Todo lo demás son fórmulas y se recalcula solo.
B7: 3. | C7: Empieza por las hojas 'Supuestos' y 'TiposDeCaso'. Con esas dos, el resto del modelo ya produce resultados.
B8: 4. | C8: La hoja 'Palancas' muestra cuánto mueve la utilidad cada cambio operativo. Es la que hay que mirar antes de decidir dónde invertir esfuerzo.
B10: Código de color
B11: Fondo amarillo | C11: Celda que tú rellenas. Es la única que se edita.
B12: Texto azul | C12: Dato de entrada escrito a mano.
B13: Texto negro | C13: Fórmula. No tocar.
B14: Texto verde | C14: Enlace a otra hoja del mismo archivo.
B16: Las hojas
B17: Supuestos | C17: Costos fijos, costo por hora de cada rol, overhead por caso. Los cimientos del modelo.
B18: TiposDeCaso | C18: Una fila por tipo de caso: precio, horas de entrega, CAC y volumen. Aquí se ve qué producto sostiene la firma y cuál la subsidia.
B19: Embudo | C19: Consultas, consultas atendidas y casos firmados, mes a mes. Calcula la tasa de conversión, que es la palanca de mayor retorno.
B20: Firma | C20: El estado de resultados: ingreso, margen de contribución, costos fijos, utilidad y punto de equilibrio.
B21: Palancas | C21: Qué pasa con la utilidad si mueves conversión, horas de entrega, precio o CAC. Ordenadas por impacto.
B22: Panel | C22: Los cinco números del lunes por la mañana.
B24: Advertencia
C25: Este modelo no constituye asesoría legal, fiscal ni contable. El saldo de la cuenta fiduciaria (IOLTA) NO es liquidez de la firma y no debe cargarse en ninguna celda de caja de este archivo: los fondos del cliente no devengados no son ingreso ni activo de la firma.

Sheet Supuestos
A1: Supuestos
A2: Celdas amarillas = rellenar. Valores precargados ilustrativos.
A4: Concepto | B4: Valor | C4: Unidad | D4: Nota
A5: Costo cargado por hora — abogado | B5: 95 | C5: $ / hora | D5: Salario + carga + beneficios ÷ horas trabajadas al año. NO es la tarifa que se cobra.
A6: Costo cargado por hora — paralegal | B6: 34 | C6: $ / hora | D6: Mismo cálculo para el rol de paralegal.
A7: Costo cargado por hora — asistente/intake | B7: 24 | C7: $ / hora | D7: Personal de recepción y gestión de expediente.
A8: Overhead asignado por caso | B8: 840 | C8: $ / caso | D8: Costos fijos ÷ casos al año. Recalcular cada año.
A9: Costos fijos anuales | B9: 600000 | C9: $ / año | D9: Renta, nómina no imputable a casos, software, seguros, colegiación.
A10: Gasto de marketing mensual | B10: 24000 | C10: $ / mes | D10: Todo el gasto de captación: SEO, pago, contenido, eventos.
A11: Meses del ejercicio | B11: 12 | C11: meses | D11: Normalmente 12. Cambiar solo para un ejercicio parcial.
A14: Referencias usadas por el resto del modelo
A15: Tarifa abogado | B15: =B5 -> 95

Sheet TiposDeCaso
A1: Economía por tipo de caso
A2: El corazón del modelo. Precio − CAC − costo de entrega − overhead = margen de contribución.
A4: Tipo de caso | B4: Precio ($) | C4: Horas abogado | D4: Horas paralegal | E4: CAC ($) | F4: Casos por mes | G4: Costo de entrega ($) | H4: Overhead ($) | I4: Margen por caso ($) | J4: Margen % | K4: Ingreso anual ($) | L4: Margen anual ($)
A5: Naturalización | B5: 1800 | C5: 1 | D5: 3 | E5: 420 | F5: 12 | G5: =C5*Supuestos!$B$5+D5*Supuestos!$B$6 -> 197 | H5: =Supuestos!$B$8 -> 840 | I5: =B5-E5-G5-H5 -> 343 | J5: =IFERROR(I5/B5,0) -> 0.19055556 | K5: =B5*F5*Supuestos!$B$11 -> 259200 | L5: =I5*F5*Supuestos!$B$11 -> 49392
A6: Petición familiar (I-130) | B6: 2600 | C6: 1.5 | D6: 4 | E6: 560 | F6: 10 | G6: =C6*Supuestos!$B$5+D6*Supuestos!$B$6 -> 278.5 | H6: =Supuestos!$B$8 -> 840 | I6: =B6-E6-G6-H6 -> 921.5 | J6: =IFERROR(I6/B6,0) -> 0.35442308 | K6: =B6*F6*Supuestos!$B$11 -> 312000 | L6: =I6*F6*Supuestos!$B$11 -> 110580
A7: Ajuste de estatus | B7: 4200 | C7: 2 | D7: 4.5 | E7: 650 | F7: 9 | G7: =C7*Supuestos!$B$5+D7*Supuestos!$B$6 -> 343 | H7: =Supuestos!$B$8 -> 840 | I7: =B7-E7-G7-H7 -> 2367 | J7: =IFERROR(I7/B7,0) -> 0.56357143 | K7: =B7*F7*Supuestos!$B$11 -> 453600 | L7: =I7*F7*Supuestos!$B$11 -> 255636
A8: Asilo afirmativo | B8: 6500 | C8: 8 | D8: 10 | E8: 700 | F8: 4 | G8: =C8*Supuestos!$B$5+D8*Supuestos!$B$6 -> 1100 | H8: =Supuestos!$B$8 -> 840 | I8: =B8-E8-G8-H8 -> 3860 | J8: =IFERROR(I8/B8,0) -> 0.59384615 | K8: =B8*F8*Supuestos!$B$11 -> 312000 | L8: =I8*F8*Supuestos!$B$11 -> 185280
A9: Defensa en corte (removal) | B9: 9000 | C9: 20 | D9: 12 | E9: 900 | F9: 3 | G9: =C9*Supuestos!$B$5+D9*Supuestos!$B$6 -> 2308 | H9: =Supuestos!$B$8 -> 840 | I9: =B9-E9-G9-H9 -> 4952 | J9: =IFERROR(I9/B9,0) -> 0.55022222 | K9: =B9*F9*Supuestos!$B$11 -> 324000 | L9: =I9*F9*Supuestos!$B$11 -> 178272
A10: Preparación de habeas (alcance limitado) | B10: 2800 | C10: 1.5 | D10: 8 | E10: 300 | F10: 5 | G10: =C10*Supuestos!$B$5+D10*Supuestos!$B$6 -> 414.5 | H10: =Supuestos!$B$8 -> 840 | I10: =B10-E10-G10-H10 -> 1245.5 | J10: =IFERROR(I10/B10,0) -> 0.44482143 | K10: =B10*F10*Supuestos!$B$11 -> 168000 | L10: =I10*F10*Supuestos!$B$11 -> 74730
A11: Cumplimiento I-9 (empleador, anual) | B11: 7200 | C11: 6 | D11: 10 | E11: 1200 | F11: 0.5 | G11: =C11*Supuestos!$B$5+D11*Supuestos!$B$6 -> 910 | H11: =Supuestos!$B$8 -> 840 | I11: =B11-E11-G11-H11 -> 4250 | J11: =IFERROR(I11/B11,0) -> 0.59027778 | K11: =B11*F11*Supuestos!$B$11 -> 43200 | L11: =I11*F11*Supuestos!$B$11 -> 25500
A12: TOTAL | F12: =SUM(F5:F11) -> 43.5 | I12: =IFERROR(SUMPRODUCT(I5:I11,F5:F11)/SUM(F5:F11),0) -> 1684.6552 | J12: =IFERROR(L12/K12,0) -> 0.46975962 | K12: =SUM(K5:K11) -> 1872000 | L12: =SUM(L5:L11) -> 879390
A14: Cómo leer esta tabla
A15: • La columna 'Margen %' ordena los productos: el de arriba sostiene la firma, el de abajo puede estar subsidiándose.
A16: • 'Horas abogado' y 'Horas paralegal' son las horas REALES de entrega, no las facturables. Hay que medirlas aunque no se facturen: sin ellas no se sabe el margen.
A17: • Bajar una hora de abogado en un tipo de caso de alto volumen vale más que subir el precio de uno de bajo volumen. La hoja 'Palancas' lo cuantifica.
A18: • El overhead por caso sale de Supuestos!B8 y es igual para todos. Si un tipo de caso consume mucho más espacio o soporte, conviene asignarle un overhead propio.

Sheet Embudo
A1: Embudo de captación
A2: La conversión de consulta es la palanca de mayor retorno de la firma. Medirla semanalmente.
A4: Mes | B4: Consultas recibidas | C4: Consultas atendidas | D4: Casos firmados | E4: % atendidas | F4: % conversión | G4: Gasto de marketing ($) | H4: CAC ($)
A5: Ene | B5: 150 | C5: 120 | D5: 42 | E5: =IFERROR(C5/B5,"") -> 0.8 | F5: =IFERROR(D5/C5,"") -> 0.35 | G5: =Supuestos!$B$10 -> 24000 | H5: =IFERROR(G5/D5,"") -> 571.42857
A6: Feb | B6: 140 | C6: 112 | D6: 39 | E6: =IFERROR(C6/B6,"") -> 0.8 | F6: =IFERROR(D6/C6,"") -> 0.34821429 | G6: =Supuestos!$B$10 -> 24000 | H6: =IFERROR(G6/D6,"") -> 615.38462
A7: Mar | E7: =IFERROR(C7/B7,"") | F7: =IFERROR(D7/C7,"") | G7: =Supuestos!$B$10 -> 24000 | H7: =IFERROR(G7/D7,"")
A8: Abr | E8: =IFERROR(C8/B8,"") | F8: =IFERROR(D8/C8,"") | G8: =Supuestos!$B$10 -> 24000 | H8: =IFERROR(G8/D8,"")
A9: May | E9: =IFERROR(C9/B9,"") | F9: =IFERROR(D9/C9,"") | G9: =Supuestos!$B$10 -> 24000 | H9: =IFERROR(G9/D9,"")
A10: Jun | E10: =IFERROR(C10/B10,"") | F10: =IFERROR(D10/C10,"") | G10: =Supuestos!$B$10 -> 24000 | H10: =IFERROR(G10/D10,"")
A11: Jul | E11: =IFERROR(C11/B11,"") | F11: =IFERROR(D11/C11,"") | G11: =Supuestos!$B$10 -> 24000 | H11: =IFERROR(G11/D11,"")
A12: Ago | E12: =IFERROR(C12/B12,"") | F12: =IFERROR(D12/C12,"") | G12: =Supuestos!$B$10 -> 24000 | H12: =IFERROR(G12/D12,"")
A13: Sep | E13: =IFERROR(C13/B13,"") | F13: =IFERROR(D13/C13,"") | G13: =Supuestos!$B$10 -> 24000 | H13: =IFERROR(G13/D13,"")
A14: Oct | E14: =IFERROR(C14/B14,"") | F14: =IFERROR(D14/C14,"") | G14: =Supuestos!$B$10 -> 24000 | H14: =IFERROR(G14/D14,"")
A15: Nov | E15: =IFERROR(C15/B15,"") | F15: =IFERROR(D15/C15,"") | G15: =Supuestos!$B$10 -> 24000 | H15: =IFERROR(G15/D15,"")
A16: Dic | E16: =IFERROR(C16/B16,"") | F16: =IFERROR(D16/C16,"") | G16: =Supuestos!$B$10 -> 24000 | H16: =IFERROR(G16/D16,"")
A17: TOTAL / PROMEDIO | B17: =SUM(B5:B16) -> 290 | C17: =SUM(C5:C16) -> 232 | D17: =SUM(D5:D16) -> 81 | E17: =IFERROR(C17/B17,"") -> 0.8 | F17: =IFERROR(D17/C17,"") -> 0.34913793 | G17: =SUMIF(D5:D16,">0",G5:G16) -> 48000 | H17: =IFERROR(G17/D17,"") -> 592.59259
A19: Los tres puntos donde se pierde una consulta, por orden de frecuencia:
A20: 1. Tiempo de respuesta. Una consulta contestada en una hora convierte mucho mejor que una contestada al día siguiente.
A21: 2. Quién atiende. La persona equivocada, entre dos audiencias, con prisa.
A22: 3. Si se pide el cierre. Muchas consultas acaban en «piénselo y nos llama» en vez de en una decisión.

Sheet Firma
A1: Estado de resultados y punto de equilibrio
A2: Todo se alimenta de 'TiposDeCaso' y 'Supuestos'. No hay nada que rellenar aquí.
A4: Concepto | B4: Valor | C4: Nota
A5: Ingreso anual | B5: =TiposDeCaso!K12 -> 1872000 | C5: Suma del ingreso de todos los tipos de caso.
A6: Margen de contribución anual | B6: =TiposDeCaso!L12 -> 879390 | C6: Lo que queda tras CAC, entrega y overhead, antes de costos fijos.
A7: Margen de contribución (%) | B7: =IFERROR(B6/B5,0) -> 0.46975962 | C7: Si baja por debajo del 40 % conviene revisar el mix de casos.
A8: Costos fijos anuales | B8: =Supuestos!B9 -> 600000 | C8: Desde 'Supuestos'.
A9: Utilidad operativa | B9: =B6-B8 -> 279390 | C9: Margen de contribución menos costos fijos.
A10: Margen operativo (%) | B10: =IFERROR(B9/B5,0) -> 0.14924679 | C10: Referencia de firma de consumidor: ~25 %.
A12: Margen por caso (ponderado) | B12: =TiposDeCaso!I12 -> 1684.6552 | C12: Promedio ponderado por volumen, no promedio simple.
A13: Casos al año para cubrir los costos fijos | B13: =IFERROR(B8/B12,0) -> 356.15597 | C13: Punto de equilibrio en número de casos.
A14: Casos al mes para cubrir los costos fijos | B14: =IFERROR(B13/Supuestos!B11,0) -> 29.679664 | C14: El número que hay que superar cada mes.
A15: Casos al mes que tenemos hoy | B15: =TiposDeCaso!F12 -> 43.5 | C15: Desde 'TiposDeCaso'.
A16: Colchón sobre el equilibrio | B16: =IFERROR(B15/B14-1,0) -> 0.46565 | C16: Cuánto puede caer el volumen antes de entrar en pérdidas.

Sheet Palancas
A1: Palancas — cuánto mueve cada cambio
A2: Cambia los valores amarillos y compara. Ordenadas por impacto típico, no por facilidad.
A4: Palanca | B4: Cambio propuesto | C4: Efecto por caso ($) | D4: Efecto anual ($) | E4: ¿Cuesta dinero?
A5: Escenario base (desde las otras hojas)
A6: Casos al año | B6: =TiposDeCaso!F12*Supuestos!B11 -> 522
A7: Margen por caso hoy (ponderado) | B7: =TiposDeCaso!I12 -> 1684.6552
A8: Tasa de conversión actual | B8: =Embudo!$F$17 -> 0.34913793
A9: Utilidad operativa hoy | B9: =Firma!B9 -> 279390
A11: Palancas (edita la columna amarilla)
A12: Palanca | B12: Cambio propuesto | C12: Efecto por caso ($) | D12: Efecto anual ($) | E12: Comentario
A13: Conversión de consulta | B13: 0.1 | C13: n/a | D13: =IFERROR($B$6*(B13/$B$8)*$B$7,0) -> 251874.67 | E13: Sube la conversión N PUNTOS porcentuales. Actúa sobre el volumen, no sobre el margen por caso: más casos con el mismo gasto de marketing. No cuesta dinero — esa consulta ya se pagó.
A14: Horas de abogado por caso | B14: -1 | C14: =-B14*Supuestos!$B$5 -> 95 | D14: =C14*$B$6 -> 49590 | E14: Reduce N horas de abogado por caso moviendo trabajo al paralegal o al proceso.
A15: Horas de paralegal por caso | B15: -1 | C15: =-B15*Supuestos!$B$6 -> 34 | D15: =C15*$B$6 -> 17748 | E15: Reduce N horas de paralegal por caso mediante plantillas y automatización.
A16: Precio | B16: 0.08 | C16: =IFERROR(TiposDeCaso!K12/$B$6*B16,0) -> 286.89655 | D16: =C16*$B$6 -> 149760 | E16: Sube el precio un N %. Sin costo directo, pero con riesgo comercial.
A17: CAC | B17: -150 | C17: =-B17 -> 150 | D17: =C17*$B$6 -> 78300 | E17: Baja el CAC N dólares desplazando la mezcla de canales hacia referidos.
A18: Efecto combinado sobre la utilidad | D18: =SUM(D13:D17) -> 547272.67
A19: Utilidad operativa resultante | D19: =$B$9+D18 -> 826662.67
A21: • El efecto de la conversión se calcula sobre el volumen: más casos con el mismo gasto de marketing y el mismo margen por caso.
A22: • Las palancas se multiplican, no se suman: mejorar cinco cosas un 5 % da alrededor de +28 %, no +25 %. Este cuadro las suma de forma conservadora.
A23: • La columna 'Valor propuesto' admite valores negativos. Sirve también para medir el daño: qué pasa si el CAC sube o si las horas de entrega crecen.

Sheet Panel
A1: Panel — los cinco números del lunes por la mañana
A2: Media hoja, una vez al mes, misma fecha. La disciplina de mirarlos vale más que la sofisticación de calcularlos.
A4: # | B4: Indicador | C4: Valor | D4: Referencia sana | E4: Qué hacer si se sale
A5: 1 | B5: Casos firmados al año | C5: =TiposDeCaso!F12*Supuestos!B11 -> 522 | D5: Por encima del equilibrio | E5: Si cae por debajo de 'Firma'!B13, la firma pierde dinero ese año.
A6: 2 | B6: Tasa de conversión de consulta | C6: =Embudo!$F$17 -> 0.34913793 | D6: 40 % o más | E6: Revisar tiempo de respuesta, quién atiende y si se pide el cierre.
A7: 3 | B7: Utilidad operativa | C7: =Firma!B9 -> 279390 | D7: Positiva y creciente | E7: Si baja con ingreso estable, el problema está en el costo de entrega.
A8: 4 | B8: Margen de contribución (%) | C8: =Firma!B7 -> 0.46975962 | D8: 45 % o más | E8: Si baja, mirar la columna 'Margen %' de TiposDeCaso: hay un producto subsidiado.
A9: 5 | B9: Colchón sobre el punto de equilibrio | C9: =Firma!B16 -> 0.46565 | D9: 30 % o más | E9: Por debajo del 15 %, cualquier mes malo compromete la nómina.
B11: Dos señales de alarma que se vigilan aparte
B12: • Concentración de canal — si el 70 % de los casos viene de una sola fuente, esa fuente es un punto único de fallo.
B13: • Días entre firma del caso y cobro íntegro — es el primer síntoma de casi cualquier problema de gestión, mucho antes de que se vea en la utilidad.
